unboil_sqlalchemy_mixins/__init__.py
unboil_sqlalchemy_mixins/identifiable.py
unboil_sqlalchemy_mixins/tenant_owned.py
unboil_sqlalchemy_mixins/timestamped.py
unboil_sqlalchemy_mixins/user_owned.py
unboil_sqlalchemy_mixins-0.1.14.dist-info/METADATA
unboil_sqlalchemy_mixins-0.1.14.dist-info/WHEEL
unboil_sqlalchemy_mixins-0.1.14.dist-info/licenses/LICENSE
unboil_sqlalchemy_mixins-0.1.14.dist-info/RECORD
