Metadata-Version: 2.4
Name: unboil-sqlalchemy-mixins
Version: 0.1.14
Summary: A library providing reusable mixins for SQLAlchemy models.
Project-URL: homepage, https://github.com/eyueldk/unboil-sqlalchemy-mixins
Project-URL: repository, https://github.com/eyueldk/unboil-sqlalchemy-mixins
Author: eyueldk
License: MIT
License-File: LICENSE
Keywords: mixins,sqlalchemy,unboil
Classifier: License :: OSI Approved :: MIT License
Classifier: Operating System :: OS Independent
Classifier: Programming Language :: Python :: 3
Classifier: Programming Language :: Python :: 3.9
Requires-Python: >=3.9
Requires-Dist: sqlalchemy>=2.0.0
